devaci_module/__init__.py
devaci_module/cobra.py
devaci_module/deploy.py
devaci_module/jinja.py
devaci_module-1.4.5.dist-info/LICENSE
devaci_module-1.4.5.dist-info/METADATA
devaci_module-1.4.5.dist-info/WHEEL
devaci_module-1.4.5.dist-info/top_level.txt
devaci_module-1.4.5.dist-info/RECORD
