Metadata-Version: 2.1
Name: devaci-module
Version: 1.4.5
Summary: A Python library providing programmatic access to Cisco ACI via the official Cobra SDK.
Home-page: https://github.com/cocuni80/devaci_module
Author: Jorge Riveros
Author-email: christian.riveros@outlook.com
License: MIT
Platform: UNKNOWN
Classifier: Programming Language :: Python :: 3
Classifier: License :: OSI Approved :: MIT License
Classifier: Operating System :: OS Independent
Requires-Python: >=3.9.2
Requires-Dist: urllib3
Requires-Dist: dotenv
Requires-Dist: pathlib
Requires-Dist: Jinja2
Requires-Dist: PyYAML
Requires-Dist: pandas
Requires-Dist: openpyxl
Requires-Dist: rich
Requires-Dist: acicobra
Requires-Dist: acimodel
